imgbase64/__init__.py
imgbase64/__main__.py
imgbase64/imgbase64.py
imgbase64-0.1.6.dist-info/METADATA
imgbase64-0.1.6.dist-info/WHEEL
imgbase64-0.1.6.dist-info/top_level.txt
imgbase64-0.1.6.dist-info/RECORD
