Metadata-Version: 2.1
Name: imgbase64
Version: 0.1.6
Summary: transform images into base64
Home-page: https://github.com/Ronnasayd/imgbase64
Author: Ronnasayd de Sousa Machado
Author-email: ronnasayd@hotmail.com
License: MIT License
Keywords: image bas64 url
Platform: UNKNOWN
Requires-Dist: argparse
Requires-Dist: requests
